<?xml version="1.0" encoding="utf-8" ?><dwsync><file name=".DS_Store" server="solofy.beantownthemes.com/html/" local="3570603024" remote="-4611806634681156008" /><file name="index.php" server="solofy.beantownthemes.com/html/" local="3503901052" remote="-4611806634681156008" /><file name="closedhand.cur" server="solofy.beantownthemes.com/html/" local="3472810881" remote="-4611806634681156008" /><file name="layers.css" server="solofy.beantownthemes.com/html/" local="3607967708" remote="732207471339117656" /><file name="settings.css" server="solofy.beantownthemes.com/html/" local="3592401684" remote="-4611806634681156008" /><file name="openhand.cur" server="solofy.beantownthemes.com/html/" local="3472810892" remote="-4611806634681156008" /><file name="tp-color-picker.css" server="solofy.beantownthemes.com/html/" local="3570532257" remote="-4611806634681156008" /><file name="navigation.css" server="solofy.beantownthemes.com/html/" local="3560149379" remote="-4611806634681156008" /><file name="settings-source.css" server="solofy.beantownthemes.com/html/" local="3578290399" remote="-4611806634681156008" /></dwsync>